{"crew":[{"name":"Ken","title":"Doctor","clearance":"2","hunger":"7","morale":"7","is_alive":"1","_inuse":"1"},{"name":"Will","title":"Engineer","clearance":"3","hunger":"7","morale":"7","is_alive":"1","_inuse":"1"},{"name":"Tom","title":"Phsycologist","clearance":"4","hunger":"7","morale":"7","is_alive":"1","_inuse":"1"},{"name":"Rich","title":"Programmer","clearance":"5","hunger":"10","morale":"7","is_alive":"1","_inuse":"1"},{"name":"Ralph","title":"Painter","clearance":"6","hunger":"0","morale":"9","is_alive":"0","_inuse":"1"}],"food":"33"}